freddy_backend_client-0.1.1.dist-info/licenses/LICENSE
freddy_client/__init__.py
freddy_client/client.py
freddy_client/errors.py
freddy_client/types.py
freddy_client/api/__init__.py
freddy_client/api/admin_cache/__init__.py
freddy_client/api/admin_cache/clear_all_caches_v1_admin_cache_clear_all_post.py
freddy_client/api/admin_cache/invalidate_limit_caches_v1_admin_cache_invalidate_limits_post.py
freddy_client/api/analytics_api_keys/__init__.py
freddy_client/api/analytics_api_keys/get_api_key_daily_usage_v1_analytics_api_keys_daily_org_id_get.py
freddy_client/api/analytics_api_keys/get_api_key_usage_summary_v1_analytics_api_keys_summary_org_id_get.py
freddy_client/api/analytics_limits/__init__.py
freddy_client/api/analytics_limits/get_api_key_usage_v1_analytics_api_keys_usage_org_id_api_key_id_get.py
freddy_client/api/analytics_limits/get_usage_limits_v1_analytics_usage_limits_org_id_get.py
freddy_client/api/analytics_limits/update_usage_limits_v1_analytics_usage_limits_org_id_put.py
freddy_client/api/analytics_usage/__init__.py
freddy_client/api/analytics_usage/get_daily_usage_v1_analytics_usage_daily_org_id_get.py
freddy_client/api/analytics_usage/get_hourly_usage_v1_analytics_usage_hourly_org_id_get.py
freddy_client/api/analytics_usage/get_monthly_usage_v1_analytics_usage_monthly_org_id_get.py
freddy_client/api/analytics_usage/get_usage_benchmarks_v1_analytics_usage_benchmarks_org_id_get.py
freddy_client/api/analytics_usage/get_usage_dashboard_v1_analytics_usage_dashboard_org_id_get.py
freddy_client/api/analytics_usage/get_usage_heatmap_v1_analytics_usage_heatmap_org_id_get.py
freddy_client/api/analytics_usage/get_usage_optimization_v1_analytics_usage_optimization_org_id_get.py
freddy_client/api/analytics_usage/get_usage_summary_v1_analytics_usage_summary_org_id_get.py
freddy_client/api/analytics_usage/get_usage_trends_v1_analytics_usage_trends_org_id_get.py
freddy_client/api/analytics_usage/get_yearly_usage_v1_analytics_usage_yearly_org_id_get.py
freddy_client/api/api_keys/__init__.py
freddy_backend_client-0.1.1.dist-info/METADATA
freddy_backend_client-0.1.1.dist-info/WHEEL
freddy_backend_client-0.1.1.dist-info/top_level.txt
freddy_backend_client-0.1.1.dist-info/RECORD
