Metadata-Version: 2.4
Name: freddy-backend-client
Version: 0.1.1
Summary: Python client for Freddy Backend API
Author-email: Ananthu <ananthu.mn@aitronos.com>
License-Expression: MIT
Project-URL: Homepage, https://github.com/Aitronos-Development/freddy-backend-client
Project-URL: Documentation, https://github.com/Aitronos-Development/freddy-backend-client/blob/main/README.md
Project-URL: Repository, https://github.com/Aitronos-Development/freddy-backend-client
Keywords: freddy,api,client,backend
Classifier: Development Status :: 4 - Beta
Classifier: Intended Audience :: Developers
Classifier: Programming Language :: Python :: 3
Classifier: Programming Language :: Python :: 3.8
Classifier: Programming Language :: Python :: 3.9
Classifier: Programming Language :: Python :: 3.10
Classifier: Programming Language :: Python :: 3.11
Classifier: Programming Language :: Python :: 3.12
Classifier: Programming Language :: Python :: 3.13
Requires-Python: >=3.8
License-File: LICENSE
Requires-Dist: httpx>=0.20.0
Requires-Dist: attrs>=21.3.0
Requires-Dist: python-dateutil>=2.8.0
Dynamic: license-file
